tossip/Tossip.py
tossip/__init__.py
tossip/functions.py
tossip-0.1.5.dist-info/LICENSE
tossip-0.1.5.dist-info/METADATA
tossip-0.1.5.dist-info/WHEEL
tossip-0.1.5.dist-info/top_level.txt
tossip-0.1.5.dist-info/RECORD
