Metadata-Version: 2.1
Name: tossip
Version: 0.1.5
Summary: A library to easily communicate with iOS Devices.
Home-page: https://github.com/liquiddevelopmentnet/tossip
Author: LiquidDevelopment
License: MIT
Platform: UNKNOWN
